{
  "id": "seed-20260407-dac04762",
  "truth": "Kindness \u2014 chrestotes \u2014 useful goodness. Not mere niceness but the quality of being genuinely serviceable. A kind tool fits the hand perfectly.",
  "source": "Galatians 5:22, Hebrew: chesed (overlaps with love), Titus 3:4",
  "domain": "religion",
  "stage": "seed",
  "depth": 0.0,
  "planted_by": "beta",
  "planted_at": "2026-04-07T10:39:57+00:00",
  "waterings": [],
  "connections": [],
  "applications": [],
  "harvests": [],
  "pruned": false,
  "total_tokens": 0
}